base/Memoria.py
base/__init__.py
gerador/Palavra.py
gerador/__init__.py
projetopypiALOUIA11-0.0.1.dist-info/LICENSE
projetopypiALOUIA11-0.0.1.dist-info/METADATA
projetopypiALOUIA11-0.0.1.dist-info/WHEEL
projetopypiALOUIA11-0.0.1.dist-info/top_level.txt
projetopypiALOUIA11-0.0.1.dist-info/RECORD
