Metadata-Version: 2.1
Name: projetopypiALOUIA11
Version: 0.0.1
Summary: Pacote python para gerar palavras dissílabas
Author: Rafael Juliano
Author-email: rafael22070063@aluno.cesupa.br
License: MIT License
Keywords: Pacote
License-File: LICENSE
Requires-Dist: random
